setup.py
chef_ssh.egg-info/PKG-INFO
chef_ssh.egg-info/SOURCES.txt
chef_ssh.egg-info/dependency_links.txt
chef_ssh.egg-info/entry_points.txt
chef_ssh.egg-info/requires.txt
chef_ssh.egg-info/top_level.txt
chefssh/__init__.py
chefssh/commandbase.py
chefssh/entry.py
chefssh/scp.py
chefssh/ssh.py