Metadata-Version: 1.1
Name: chef-ssh
Version: 0.1
Summary: Chef SSH is a tool to easily query the Chef server's inventory for running scp/ssh to/from the machines
Home-page: https://github.com/omribahumi/chefssh
Author: Omri Bahumi
Author-email: omri.il@gmail.com
License: UNKNOWN
Platform: UNKNOWN
Classifier: Development Status :: 5 - Production/Stable
Classifier: Environment :: Console
Classifier: Intended Audience :: Developers
Classifier: Intended Audience :: System Administrators
Classifier: Operating System :: OS Independent
Classifier: Programming Language :: Python :: 2.7
Classifier: Topic :: System :: Clustering
Classifier: Topic :: System :: Systems Administration
Classifier: Topic :: Utilities
